[
  {
    "creator": "admin",
    "createTime": "2022-09-30 01:44:13.96",
    "modifier": null,
    "modifyTime": "2022-09-30 01:44:13.96",
    "createStaffId": 1,
    "modifyStaffId": null,
    "valid": true,
    "id": 2753031496746576,
    "code": "2022093000646",
    "processId": 2687925953906256,
    "materialCode": "125244",
    "materialName": "有机硅生胶\\GUM 795 A2 SFG\\散装",
    "specifications": "#3BAFDA",
    "materialAttribute": "半成品",
    "equipName": null,
    "workShopName": null,
    "factoryName": null,
    "equipCode": null,
    "deviceCode": null,
    "deviceName": null,
    "soipEn02": "8047-GUM-CTN",
    "soipLevel2": null,
    "bomId": 1,
    "manuVersion": "A001",
    "scheduleNum": 330.912,
    "unDeliveryNum": 54.0,
    "unit": "KG",
    "yy": 0,
    "scheduleDuration": "0.000000",
    "scheduleMaterialCost": null,
    "batchCode": null,
    "scheduleStartDate": "2022-10-01 00:00:00",
    "scheduleEndDate": "2022-10-01 08:00:00",
    "manuStartDate": null,
    "manuEndDate": null,
    "productionDate": null,
    "manuDate": null,
    "actualNum": null,
    "manuDuration": null,
    "manuMaterialCost": null,
    "remarks": null,
    "remark1": "",
    "status": "0",
    "orderCode": "HT220614085000002",
    "bu": "江西星火硅橡胶部",
    "requestDate": "2022-09-03",
    "confirmDate": "2022-08-03",
    "saleCertificate": "1038983",
    "projectCode": "91",
    "sellerName": "广州龙升橡胶制品有限公司",
    "headRemark": "",
    "stockAddr": "",
    "businessManager": "丁伟",
    "sort": 2,
    "orgId": 1000
  }
]
